ffmpegio_plugin_static_ffmpeg/__init__.py
ffmpegio_plugin_static_ffmpeg-0.1.0.dist-info/LICENSE
ffmpegio_plugin_static_ffmpeg-0.1.0.dist-info/METADATA
ffmpegio_plugin_static_ffmpeg-0.1.0.dist-info/WHEEL
ffmpegio_plugin_static_ffmpeg-0.1.0.dist-info/entry_points.txt
ffmpegio_plugin_static_ffmpeg-0.1.0.dist-info/top_level.txt
ffmpegio_plugin_static_ffmpeg-0.1.0.dist-info/RECORD
