Metadata-Version: 2.1
Name: ffmpegio-plugin-static-ffmpeg
Version: 0.1.0
Summary: ffmpegio finder plugin to use FFmpeg executables from static-ffmpeg package
Home-page: https://python-ffmpegio.github.io/python-ffmpegio-plugin-static-ffmpeg
License: GPL-2.0 License
Project-URL: Repository, https://github.com/python-ffmpegio/python-ffmpegio-plugin-static-ffmpeg
Project-URL: Issues, https://github.com/python-ffmpegio/python-ffmpegio-plugin-static-ffmpeg/issues
Project-URL: Pull Requests, https://github.com/python-ffmpegio/python-ffmpegio-plugin-static-ffmpeg/pulls
Keywords: multimedia,ffmpeg
Platform: UNKNOWN
Classifier: Development Status :: 4 - Beta
Classifier: License :: OSI Approved :: GNU General Public License v2 (GPLv2)
Classifier: Topic :: Multimedia :: Sound/Audio
Classifier: Topic :: Multimedia :: Sound/Audio :: Capture/Recording
Classifier: Topic :: Multimedia :: Sound/Audio :: Conversion
Classifier: Topic :: Multimedia :: Video
Classifier: Topic :: Multimedia :: Video :: Capture
Classifier: Topic :: Multimedia :: Video :: Conversion
Classifier: Programming Language :: Python :: 3.7
Classifier: Programming Language :: Python :: 3.8
Classifier: Programming Language :: Python :: 3.9
Classifier: Programming Language :: Python :: 3.10
Requires-Python: >=3.7
License-File: LICENSE
Requires-Dist: static-ffmpeg
Requires-Dist: pluggy
